{"version":1,"resource":"file:///home/brian/repos-geocom/release-automation-pipelines/Pipelines/Generic/generic-release-pipeline.groovy","entries":[{"id":"diOA.groovy","timestamp":1713466407278},{"id":"du4B.groovy","timestamp":1713466577454},{"id":"9jg7.groovy","timestamp":1713466875142},{"id":"Xdur.groovy","timestamp":1713466885838},{"id":"Bvc2.groovy","timestamp":1713469484850},{"id":"fxLP.groovy","timestamp":1713469531886},{"id":"j6aj.groovy","timestamp":1713469592258},{"id":"XqX4.groovy","timestamp":1713469650290},{"id":"EvWB.groovy","timestamp":1713470392302},{"id":"NgaE.groovy","timestamp":1713473238759},{"id":"naKF.groovy","timestamp":1713541566667},{"id":"YE55.groovy","timestamp":1713541666224},{"id":"jDMH.groovy","source":"undoRedo.source","timestamp":1713541669160},{"id":"njdR.groovy","timestamp":1713542571866},{"id":"8wAF.groovy","timestamp":1713542719659},{"id":"3g5d.groovy","timestamp":1713542805424},{"id":"i16X.groovy","timestamp":1713542846061},{"id":"3YkJ.groovy","timestamp":1713543137136},{"id":"U0YI.groovy","timestamp":1713543308162},{"id":"C1h8.groovy","source":"undoRedo.source","timestamp":1713543816176},{"id":"nypz.groovy","timestamp":1713551238714},{"id":"Xcgn.groovy","timestamp":1713552684876},{"id":"gloq.groovy","timestamp":1713552843562},{"id":"XIO8.groovy","timestamp":1713553041182},{"id":"s09u.groovy","timestamp":1713553187521},{"id":"ZnTl.groovy","source":"undoRedo.source","timestamp":1713878666767},{"id":"2Hro.groovy","timestamp":1713878878339},{"id":"Ccp0.groovy","source":"undoRedo.source","timestamp":1713878996455},{"id":"IyPv.groovy","timestamp":1713880276963},{"id":"iYf8.groovy","timestamp":1713880650815},{"id":"ivNV.groovy","timestamp":1713881951647},{"id":"2D03.groovy","timestamp":1713882302895},{"id":"AZw7.groovy","timestamp":1713883525535},{"id":"SrrT.groovy","timestamp":1713885824711},{"id":"QVo3.groovy","timestamp":1713894018995},{"id":"jZ5X.groovy","timestamp":1713894110219},{"id":"bS6m.groovy","source":"undoRedo.source","timestamp":1713894165431},{"id":"hOy2.groovy","timestamp":1713896003843},{"id":"reAh.groovy","timestamp":1713896205199},{"id":"dtae.groovy","timestamp":1713902222519},{"id":"6GuD.groovy","source":"undoRedo.source","timestamp":1713902590527},{"id":"Nvne.groovy","timestamp":1713903597855},{"id":"lx84.groovy","timestamp":1713904715615},{"id":"F7ru.groovy","timestamp":1713905116067},{"id":"r2dA.groovy","timestamp":1713905285635},{"id":"bTLa.groovy","timestamp":1713905343871},{"id":"AsHj.groovy","timestamp":1713905666375},{"id":"fICh.groovy","timestamp":1713905864319},{"id":"YIlA.groovy","timestamp":1713906727443},{"id":"DWkT.groovy","timestamp":1713906844839}]}