{"version":1,"resource":"file:///home/brian/repos-geocom/kubernetes-ansible-collection/Infrastructure/Clusters/QA/runPlaybook.bash","entries":[{"id":"RDsz.bash","timestamp":1713973062076},{"id":"uoFz.bash","timestamp":1713977464616},{"id":"BvJ9.bash","timestamp":1713977487164},{"id":"RcR6.bash","source":"undoRedo.source","timestamp":1713977519688},{"id":"935p.bash","timestamp":1713978110788},{"id":"541S.bash","source":"undoRedo.source","timestamp":1713978139020},{"id":"2FlY.bash","timestamp":1714402337692},{"id":"K3lT.bash","source":"undoRedo.source","timestamp":1714402808166},{"id":"X0qn.bash","timestamp":1714405510630},{"id":"NDaL.bash","timestamp":1714413129576},{"id":"2niv.bash","timestamp":1714413188861},{"id":"7nCo.bash","timestamp":1714415523281},{"id":"5uYJ.bash","timestamp":1715004598797},{"id":"Mmpy.bash","timestamp":1715006400539},{"id":"MYYr.bash","timestamp":1715189576548},{"id":"L4ZE.bash","timestamp":1715266634081},{"id":"Y1v7.bash","timestamp":1715266898009},{"id":"ngBG.bash","timestamp":1715268264055},{"id":"cuu1.bash","timestamp":1715269146435},{"id":"Grn0.bash","timestamp":1715269166000},{"id":"Tot2.bash","timestamp":1715275944307},{"id":"lSUk.bash","source":"undoRedo.source","timestamp":1715276032681},{"id":"qSSU.bash","timestamp":1715277638171},{"id":"6iVp.bash","timestamp":1715632663675},{"id":"YBEo.bash","timestamp":1715704163710}]}